mixer_shortcode/__init__.py
mixer_shortcode/errors.py
mixer_shortcode/oauth.py
mixer_shortcode-1.0.0.dist-info/METADATA
mixer_shortcode-1.0.0.dist-info/RECORD
mixer_shortcode-1.0.0.dist-info/WHEEL
mixer_shortcode-1.0.0.dist-info/top_level.txt
